heavi/__init__.py
heavi/filtering.py
heavi/graphing.py
heavi/model.py
heavi/network.py
heavi/node.py
heavi/numeric.py
heavi/sparam.py
heavi/stochastic.py
heavi/transformations.py
heavi/base/__init__.py
heavi/base/admittance.py
heavi/base/capacitor.py
heavi/base/component.py
heavi/base/diode.py
heavi/base/impedance.py
heavi/base/inductor.py
heavi/base/nport.py
heavi/base/numeric.py
heavi/base/port.py
heavi/base/resistor.py
heavi/base/source.py
heavi/base/tl.py
heavi/lib/__init__.py
heavi/lib/emerge.py
heavi/lib/libgen.py
heavi/lib/mc.py
heavi/lib/optim.py
heavi/lib/pcb.py
heavi/lib/smd.py
heavi/lib/spice.py
heavi/lib/tl.py
heavi/lib/touchstone.py
heavi/solvers/__init__.py
heavi/solvers/acfn.py
heavi/solvers/dcfn.py
heavi/solvers/spfn.py
heavi/solvers/tranfn.py
heavi-0.7.7.dist-info/METADATA
heavi-0.7.7.dist-info/WHEEL
heavi-0.7.7.dist-info/licenses/LICENSE
heavi-0.7.7.dist-info/RECORD
