Metadata-Version: 2.4
Name: heavi
Version: 0.7.7
Summary: An RF circuit simulator
Project-URL: Homepage, https://github.com/FennisRobert/heavi
Project-URL: Issues, https://github.com/FennisRobert/heavi/issues
Author: Robert Fennis
License: MIT Lisence
License-File: LICENSE
Requires-Python: <4.0,>=3.10
Requires-Dist: loguru<0.8.0,>=0.7.3
Requires-Dist: matplotlib>=3.8.0
Requires-Dist: numba-progress>=1.1.0
Requires-Dist: numba>=0.57.0
Requires-Dist: numpy>=1.24
Requires-Dist: schemdraw>=0.19
Requires-Dist: scipy>=1.14.1
Requires-Dist: sympy<2.0.0,>=1.13.3
